pynwsspc/__init__.py
pynwsspc-0.0.1.dist-info/LICENSE
pynwsspc-0.0.1.dist-info/METADATA
pynwsspc-0.0.1.dist-info/WHEEL
pynwsspc-0.0.1.dist-info/top_level.txt
pynwsspc-0.0.1.dist-info/RECORD
