Metadata-Version: 2.1
Name: pynwsspc
Version: 0.0.1
Summary: A package retrieve NWS SPC data
Home-page: https://github.com/ntilley905/pynwsspc
Author: Nathan Tilley
Author-email: nathan@tilley.xyz
License: MIT
Project-URL: Bug Tracker, https://github.com/ntilley905/pynwsspc
Platform: UNKNOWN
Classifier: Programming Language :: Python :: 3
Classifier: License :: OSI Approved :: MIT License
Classifier: Operating System :: OS Independent
Requires-Python: >=3.6
